sddl_parser/__init__.py
sddl_parser/ace_rights_enums.py
sddl_parser/api.py
sddl_parser/enums.py
sddl_parser/parser.py
sddl_parser/parser_conditional_ace.py
sddl_parser/parser_sid.py
sddl_parser/sid_enum.py
sddl_parser/types.py
sddl_parser/well_known_dictionary.py
sddl_parser-0.6.2.dist-info/METADATA
sddl_parser-0.6.2.dist-info/WHEEL
sddl_parser-0.6.2.dist-info/RECORD
