Metadata-Version: 2.1
Name: sddl-parser
Version: 0.6.2
Summary: Parse SDDL strings
Author: Max Harley
Author-email: maxh@maxh.io
Requires-Python: >=3.10,<4.0
Classifier: Programming Language :: Python :: 3
Classifier: Programming Language :: Python :: 3.10
Classifier: Programming Language :: Python :: 3.11
Classifier: Programming Language :: Python :: 3.12
Requires-Dist: parsy (>=2.1,<3.0)
